[
  {
    "inputs": [
      {
        "internalType": "string",
        "name": "name_",
        "type": "string"
      },
      {
        "internalType": "string",
        "name": "symbol_",
        "type": "string"
      },
      {
        "internalType": "contract IWeightSource",
        "name": "weightSource_",
        "type": "address"
      },
      {
        "internalType": "uint256",
        "name": "epochLength_",
        "type": "uint256"
      },
      {
        "internalType": "uint256",
        "name": "baseEmission_",
        "type": "uint256"
      },
      {
        "internalType": "uint256",
        "name": "decayBps_",
        "type": "uint256"
      }
    ],
    "stateMutability": "nonpayable",
    "type": "constructor"
  },
  {
    "inputs": [],
    "name": "AlreadyClaimed",
    "type": "error"
  },
  {
    "inputs": [],
    "name": "AlreadyRegistered",
    "type": "error"
  },
  {
    "inputs": [],
    "name": "BadParams",
    "type": "error"
  },
  {
    "inputs": [
      {
        "internalType": "address",
        "name": "spender",
        "type": "address"
      },
      {
        "internalType": "uint256",
        "name": "allowance",
        "type": "uint256"
      },
      {
        "internalType": "uint256",
        "name": "needed",
        "type": "uint256"
      }
    ],
    "name": "ERC20InsufficientAllowance",
    "type": "error"
  },
  {
    "inputs": [
      {
        "internalType": "address",
        "name": "sender",
        "type": "address"
      },
      {
        "internalType": "uint256",
        "name": "balance",
        "type": "uint256"
      },
      {
        "internalType": "uint256",
        "name": "needed",
        "type": "uint256"
      }
    ],
    "name": "ERC20InsufficientBalance",
    "type": "error"
  },
  {
    "inputs": [
      {
        "internalType": "address",
        "name": "approver",
        "type": "address"
      }
    ],
    "name": "ERC20InvalidApprover",
    "type": "error"
  },
  {
    "inputs": [
      {
        "internalType": "address",
        "name": "receiver",
        "type": "address"
      }
    ],
    "name": "ERC20InvalidReceiver",
    "type": "error"
  },
  {
    "inputs": [
      {
        "internalType": "address",
        "name": "sender",
        "type": "address"
      }
    ],
    "name": "ERC20InvalidSender",
    "type": "error"
  },
  {
    "inputs": [
      {
        "internalType": "address",
        "name": "spender",
        "type": "address"
      }
    ],
    "name": "ERC20InvalidSpender",
    "type": "error"
  },
  {
    "inputs": [],
    "name": "EpochNotEnded",
    "type": "error"
  },
  {
    "inputs": [],
    "name": "NoWeight",
    "type": "error"
  },
  {
    "inputs": [],
    "name": "NotRegistered",
    "type": "error"
  },
  {
    "inputs": [],
    "name": "NothingToClaim",
    "type": "error"
  },
  {
    "inputs": [],
    "name": "ZeroAddress",
    "type": "error"
  },
  {
    "anonymous": false,
    "inputs": [
      {
        "indexed": true,
        "internalType": "address",
        "name": "owner",
        "type": "address"
      },
      {
        "indexed": true,
        "internalType": "address",
        "name": "spender",
        "type": "address"
      },
      {
        "indexed": false,
        "internalType": "uint256",
        "name": "value",
        "type": "uint256"
      }
    ],
    "name": "Approval",
    "type": "event"
  },
  {
    "anonymous": false,
    "inputs": [
      {
        "indexed": true,
        "internalType": "uint256",
        "name": "epoch",
        "type": "uint256"
      },
      {
        "indexed": true,
        "internalType": "address",
        "name": "account",
        "type": "address"
      },
      {
        "indexed": false,
        "internalType": "uint256",
        "name": "amount",
        "type": "uint256"
      }
    ],
    "name": "Claimed",
    "type": "event"
  },
  {
    "anonymous": false,
    "inputs": [
      {
        "indexed": true,
        "internalType": "uint256",
        "name": "epoch",
        "type": "uint256"
      },
      {
        "indexed": true,
        "internalType": "address",
        "name": "account",
        "type": "address"
      },
      {
        "indexed": false,
        "internalType": "uint256",
        "name": "weight",
        "type": "uint256"
      },
      {
        "indexed": false,
        "internalType": "uint256",
        "name": "newTotal",
        "type": "uint256"
      }
    ],
    "name": "Registered",
    "type": "event"
  },
  {
    "anonymous": false,
    "inputs": [
      {
        "indexed": true,
        "internalType": "address",
        "name": "from",
        "type": "address"
      },
      {
        "indexed": true,
        "internalType": "address",
        "name": "to",
        "type": "address"
      },
      {
        "indexed": false,
        "internalType": "uint256",
        "name": "value",
        "type": "uint256"
      }
    ],
    "name": "Transfer",
    "type": "event"
  },
  {
    "inputs": [
      {
        "internalType": "address",
        "name": "owner",
        "type": "address"
      },
      {
        "internalType": "address",
        "name": "spender",
        "type": "address"
      }
    ],
    "name": "allowance",
    "outputs": [
      {
        "internalType": "uint256",
        "name": "",
        "type": "uint256"
      }
    ],
    "stateMutability": "view",
    "type": "function"
  },
  {
    "inputs": [
      {
        "internalType": "address",
        "name": "spender",
        "type": "address"
      },
      {
        "internalType": "uint256",
        "name": "value",
        "type": "uint256"
      }
    ],
    "name": "approve",
    "outputs": [
      {
        "internalType": "bool",
        "name": "",
        "type": "bool"
      }
    ],
    "stateMutability": "nonpayable",
    "type": "function"
  },
  {
    "inputs": [
      {
        "internalType": "address",
        "name": "account",
        "type": "address"
      }
    ],
    "name": "balanceOf",
    "outputs": [
      {
        "internalType": "uint256",
        "name": "",
        "type": "uint256"
      }
    ],
    "stateMutability": "view",
    "type": "function"
  },
  {
    "inputs": [],
    "name": "baseEmission",
    "outputs": [
      {
        "internalType": "uint256",
        "name": "",
        "type": "uint256"
      }
    ],
    "stateMutability": "view",
    "type": "function"
  },
  {
    "inputs": [
      {
        "internalType": "uint256",
        "name": "epoch",
        "type": "uint256"
      }
    ],
    "name": "claimMint",
    "outputs": [
      {
        "internalType": "uint256",
        "name": "amount",
        "type": "uint256"
      }
    ],
    "stateMutability": "nonpayable",
    "type": "function"
  },
  {
    "inputs": [
      {
        "internalType": "uint256",
        "name": "epoch",
        "type": "uint256"
      },
      {
        "internalType": "address",
        "name": "account",
        "type": "address"
      }
    ],
    "name": "claimableMint",
    "outputs": [
      {
        "internalType": "uint256",
        "name": "",
        "type": "uint256"
      }
    ],
    "stateMutability": "view",
    "type": "function"
  },
  {
    "inputs": [
      {
        "internalType": "uint256",
        "name": "",
        "type": "uint256"
      },
      {
        "internalType": "address",
        "name": "",
        "type": "address"
      }
    ],
    "name": "claimed",
    "outputs": [
      {
        "internalType": "bool",
        "name": "",
        "type": "bool"
      }
    ],
    "stateMutability": "view",
    "type": "function"
  },
  {
    "inputs": [],
    "name": "currentEpoch",
    "outputs": [
      {
        "internalType": "uint256",
        "name": "",
        "type": "uint256"
      }
    ],
    "stateMutability": "view",
    "type": "function"
  },
  {
    "inputs": [],
    "name": "decayBps",
    "outputs": [
      {
        "internalType": "uint256",
        "name": "",
        "type": "uint256"
      }
    ],
    "stateMutability": "view",
    "type": "function"
  },
  {
    "inputs": [],
    "name": "decimals",
    "outputs": [
      {
        "internalType": "uint8",
        "name": "",
        "type": "uint8"
      }
    ],
    "stateMutability": "view",
    "type": "function"
  },
  {
    "inputs": [
      {
        "internalType": "uint256",
        "name": "epoch",
        "type": "uint256"
      }
    ],
    "name": "epochEmission",
    "outputs": [
      {
        "internalType": "uint256",
        "name": "emission",
        "type": "uint256"
      }
    ],
    "stateMutability": "view",
    "type": "function"
  },
  {
    "inputs": [],
    "name": "epochLength",
    "outputs": [
      {
        "internalType": "uint256",
        "name": "",
        "type": "uint256"
      }
    ],
    "stateMutability": "view",
    "type": "function"
  },
  {
    "inputs": [
      {
        "internalType": "uint256",
        "name": "",
        "type": "uint256"
      }
    ],
    "name": "epochTotalWeight",
    "outputs": [
      {
        "internalType": "uint256",
        "name": "",
        "type": "uint256"
      }
    ],
    "stateMutability": "view",
    "type": "function"
  },
  {
    "inputs": [],
    "name": "name",
    "outputs": [
      {
        "internalType": "string",
        "name": "",
        "type": "string"
      }
    ],
    "stateMutability": "view",
    "type": "function"
  },
  {
    "inputs": [],
    "name": "register",
    "outputs": [
      {
        "internalType": "uint256",
        "name": "weight",
        "type": "uint256"
      }
    ],
    "stateMutability": "nonpayable",
    "type": "function"
  },
  {
    "inputs": [
      {
        "internalType": "uint256",
        "name": "",
        "type": "uint256"
      },
      {
        "internalType": "address",
        "name": "",
        "type": "address"
      }
    ],
    "name": "registeredWeight",
    "outputs": [
      {
        "internalType": "uint256",
        "name": "",
        "type": "uint256"
      }
    ],
    "stateMutability": "view",
    "type": "function"
  },
  {
    "inputs": [],
    "name": "startEpoch",
    "outputs": [
      {
        "internalType": "uint256",
        "name": "",
        "type": "uint256"
      }
    ],
    "stateMutability": "view",
    "type": "function"
  },
  {
    "inputs": [],
    "name": "symbol",
    "outputs": [
      {
        "internalType": "string",
        "name": "",
        "type": "string"
      }
    ],
    "stateMutability": "view",
    "type": "function"
  },
  {
    "inputs": [],
    "name": "totalSupply",
    "outputs": [
      {
        "internalType": "uint256",
        "name": "",
        "type": "uint256"
      }
    ],
    "stateMutability": "view",
    "type": "function"
  },
  {
    "inputs": [
      {
        "internalType": "address",
        "name": "to",
        "type": "address"
      },
      {
        "internalType": "uint256",
        "name": "value",
        "type": "uint256"
      }
    ],
    "name": "transfer",
    "outputs": [
      {
        "internalType": "bool",
        "name": "",
        "type": "bool"
      }
    ],
    "stateMutability": "nonpayable",
    "type": "function"
  },
  {
    "inputs": [
      {
        "internalType": "address",
        "name": "from",
        "type": "address"
      },
      {
        "internalType": "address",
        "name": "to",
        "type": "address"
      },
      {
        "internalType": "uint256",
        "name": "value",
        "type": "uint256"
      }
    ],
    "name": "transferFrom",
    "outputs": [
      {
        "internalType": "bool",
        "name": "",
        "type": "bool"
      }
    ],
    "stateMutability": "nonpayable",
    "type": "function"
  },
  {
    "inputs": [],
    "name": "weightSource",
    "outputs": [
      {
        "internalType": "contract IWeightSource",
        "name": "",
        "type": "address"
      }
    ],
    "stateMutability": "view",
    "type": "function"
  }
]
